Workbook

Sheet Config
A1: Configuración
A2: Celdas amarillas = las editás vos. El resto son fórmulas, no las toques.
A4: Ingreso quincenal fijo | B4: 0
A6: Días de cobro | B6: 10 | C6: y | D6: 24
A9: Presupuesto por categoría (por quincena)
A10: Categoría | B10: Presupuesto
A11: Comida | B11: 0
A12: Transporte | B12: 0
A13: Vivienda | B13: 0
A14: Ocio | B14: 0
A15: Salud | B15: 0
A16: Ropa | B16: 0
A17: Suscripciones | B17: 0
A18: Otros | B18: 0
A19: Total presupuestado | B19: =SUM(B11:B18) -> 0

Sheet Gastos
A1: Registro de gastos
A2: Columna A-F: lo que completa el Google Form. Columna G: fórmula de período (autocalculada).
A4: Marca temporal | B4: Fecha | C4: Monto | D4: Categoría | E4: Medio de pago | F4: Nota | G4: Período
A5: 09/08/2026 10:15:00 | B5: 2026-08-09 | C5: 4500 | D5: Comida | E5: Débito | F5: Supermercado semanal | G5: =IF(DAY(B5)<Config!$B$6,TEXT(YEAR(EDATE(B5,-1)),"0000")&"-"&TEXT(MONTH(EDATE(B5,-1)),"00")&"-B",IF(DAY(B5)<Config!$D$6,TEXT(YEAR(B5),"0000")&"-"&TEXT(MONTH(B5),"00")&"-A",TEXT(YEAR(B5),"0000")&"-"&TEXT(MONTH(B5),"00")&"-B")) -> 2026-07-B
G6: =IF(B6="","",IF(DAY(B6)<Config!$B$6,TEXT(YEAR(EDATE(B6,-1)),"0000")&"-"&TEXT(MONTH(EDATE(B6,-1)),"00")&"-B",IF(DAY(B6)<Config!$D$6,TEXT(YEAR(B6),"0000")&"-"&TEXT(MONTH(B6),"00")&"-A",TEXT(YEAR(B6),"0000")&"-"&TEXT(MONTH(B6),"00")&"-B")))
G7: =IF(B7="","",IF(DAY(B7)<Config!$B$6,TEXT(YEAR(EDATE(B7,-1)),"0000")&"-"&TEXT(MONTH(EDATE(B7,-1)),"00")&"-B",IF(DAY(B7)<Config!$D$6,TEXT(YEAR(B7),"0000")&"-"&TEXT(MONTH(B7),"00")&"-A",TEXT(YEAR(B7),"0000")&"-"&TEXT(MONTH(B7),"00")&"-B")))
G8: =IF(B8="","",IF(DAY(B8)<Config!$B$6,TEXT(YEAR(EDATE(B8,-1)),"0000")&"-"&TEXT(MONTH(EDATE(B8,-1)),"00")&"-B",IF(DAY(B8)<Config!$D$6,TEXT(YEAR(B8),"0000")&"-"&TEXT(MONTH(B8),"00")&"-A",TEXT(YEAR(B8),"0000")&"-"&TEXT(MONTH(B8),"00")&"-B")))
G9: =IF(B9="","",IF(DAY(B9)<Config!$B$6,TEXT(YEAR(EDATE(B9,-1)),"0000")&"-"&TEXT(MONTH(EDATE(B9,-1)),"00")&"-B",IF(DAY(B9)<Config!$D$6,TEXT(YEAR(B9),"0000")&"-"&TEXT(MONTH(B9),"00")&"-A",TEXT(YEAR(B9),"0000")&"-"&TEXT(MONTH(B9),"00")&"-B")))
G10: =IF(B10="","",IF(DAY(B10)<Config!$B$6,TEXT(YEAR(EDATE(B10,-1)),"0000")&"-"&TEXT(MONTH(EDATE(B10,-1)),"00")&"-B",IF(DAY(B10)<Config!$D$6,TEXT(YEAR(B10),"0000")&"-"&TEXT(MONTH(B10),"00")&"-A",TEXT(YEAR(B10),"0000")&"-"&TEXT(MONTH(B10),"00")&"-B")))
G11: =IF(B11="","",IF(DAY(B11)<Config!$B$6,TEXT(YEAR(EDATE(B11,-1)),"0000")&"-"&TEXT(MONTH(EDATE(B11,-1)),"00")&"-B",IF(DAY(B11)<Config!$D$6,TEXT(YEAR(B11),"0000")&"-"&TEXT(MONTH(B11),"00")&"-A",TEXT(YEAR(B11),"0000")&"-"&TEXT(MONTH(B11),"00")&"-B")))
G12: =IF(B12="","",IF(DAY(B12)<Config!$B$6,TEXT(YEAR(EDATE(B12,-1)),"0000")&"-"&TEXT(MONTH(EDATE(B12,-1)),"00")&"-B",IF(DAY(B12)<Config!$D$6,TEXT(YEAR(B12),"0000")&"-"&TEXT(MONTH(B12),"00")&"-A",TEXT(YEAR(B12),"0000")&"-"&TEXT(MONTH(B12),"00")&"-B")))
G13: =IF(B13="","",IF(DAY(B13)<Config!$B$6,TEXT(YEAR(EDATE(B13,-1)),"0000")&"-"&TEXT(MONTH(EDATE(B13,-1)),"00")&"-B",IF(DAY(B13)<Config!$D$6,TEXT(YEAR(B13),"0000")&"-"&TEXT(MONTH(B13),"00")&"-A",TEXT(YEAR(B13),"0000")&"-"&TEXT(MONTH(B13),"00")&"-B")))
G14: =IF(B14="","",IF(DAY(B14)<Config!$B$6,TEXT(YEAR(EDATE(B14,-1)),"0000")&"-"&TEXT(MONTH(EDATE(B14,-1)),"00")&"-B",IF(DAY(B14)<Config!$D$6,TEXT(YEAR(B14),"0000")&"-"&TEXT(MONTH(B14),"00")&"-A",TEXT(YEAR(B14),"0000")&"-"&TEXT(MONTH(B14),"00")&"-B")))
G15: =IF(B15="","",IF(DAY(B15)<Config!$B$6,TEXT(YEAR(EDATE(B15,-1)),"0000")&"-"&TEXT(MONTH(EDATE(B15,-1)),"00")&"-B",IF(DAY(B15)<Config!$D$6,TEXT(YEAR(B15),"0000")&"-"&TEXT(MONTH(B15),"00")&"-A",TEXT(YEAR(B15),"0000")&"-"&TEXT(MONTH(B15),"00")&"-B")))
G16: =IF(B16="","",IF(DAY(B16)<Config!$B$6,TEXT(YEAR(EDATE(B16,-1)),"0000")&"-"&TEXT(MONTH(EDATE(B16,-1)),"00")&"-B",IF(DAY(B16)<Config!$D$6,TEXT(YEAR(B16),"0000")&"-"&TEXT(MONTH(B16),"00")&"-A",TEXT(YEAR(B16),"0000")&"-"&TEXT(MONTH(B16),"00")&"-B")))
G17: =IF(B17="","",IF(DAY(B17)<Config!$B$6,TEXT(YEAR(EDATE(B17,-1)),"0000")&"-"&TEXT(MONTH(EDATE(B17,-1)),"00")&"-B",IF(DAY(B17)<Config!$D$6,TEXT(YEAR(B17),"0000")&"-"&TEXT(MONTH(B17),"00")&"-A",TEXT(YEAR(B17),"0000")&"-"&TEXT(MONTH(B17),"00")&"-B")))
... G200: =IF(B200="","",IF(DAY(B200)<Config!$B$6,TEXT(YEAR(EDATE(B200,-1)),"0000")&"-"&TEXT(MONTH(EDATE(B200,-1)),"00")&"-B",IF(DAY(B200)<Config!$D$6,TEXT(YEAR(B200),"0000")&"-"&TEXT(MONTH(B200),"00")&"-A",TEXT(YEAR(B200),"0000")&"-"&TEXT(MONTH(B200),"00")&"-B")))

Sheet Resumen
A1: Resumen de la quincena actual
A2: Se actualiza solo según la fecha de hoy. Nada para editar acá.
A4: Período actual | B4: =IF(DAY(TODAY())<Config!$B$6,TEXT(YEAR(EDATE(TODAY(),-1)),"0000")&"-"&TEXT(MONTH(EDATE(TODAY(),-1)),"00")&"-B",IF(DAY(TODAY())<Config!$D$6,TEXT(YEAR(TODAY()),"0000")&"-"&TEXT(MONTH(TODAY()),"00")&"-A",TEXT(YEAR(TODAY()),"0000")&"-"&TEXT(MONTH(TODAY()),"00")&"-B")) -> 2026-08-A
A6: Ingreso de la quincena | B6: =Config!$B$4 -> 0
A7: Total gastado | B7: =SUMIFS(Gastos!$C$5:$C$201,Gastos!$G$5:$G$201,$B$4) -> 0
A8: Diferencia (te queda / te pasaste) | B8: =B6-B7 -> 0
A10: Desglose por categoría — período actual
A11: Categoría | B11: Presupuesto | C11: Gastado | D11: Diferencia
A12: Comida | B12: =Config!B11 -> 0 | C12: =SUMIFS(Gastos!$C$5:$C$201,Gastos!$G$5:$G$201,$B$4,Gastos!$D$5:$D$201,A12) -> 0 | D12: =B12-C12 -> 0
A13: Transporte | B13: =Config!B12 -> 0 | C13: =SUMIFS(Gastos!$C$5:$C$201,Gastos!$G$5:$G$201,$B$4,Gastos!$D$5:$D$201,A13) -> 0 | D13: =B13-C13 -> 0
A14: Vivienda | B14: =Config!B13 -> 0 | C14: =SUMIFS(Gastos!$C$5:$C$201,Gastos!$G$5:$G$201,$B$4,Gastos!$D$5:$D$201,A14) -> 0 | D14: =B14-C14 -> 0
A15: Ocio | B15: =Config!B14 -> 0 | C15: =SUMIFS(Gastos!$C$5:$C$201,Gastos!$G$5:$G$201,$B$4,Gastos!$D$5:$D$201,A15) -> 0 | D15: =B15-C15 -> 0
A16: Salud | B16: =Config!B15 -> 0 | C16: =SUMIFS(Gastos!$C$5:$C$201,Gastos!$G$5:$G$201,$B$4,Gastos!$D$5:$D$201,A16) -> 0 | D16: =B16-C16 -> 0
A17: Ropa | B17: =Config!B16 -> 0 | C17: =SUMIFS(Gastos!$C$5:$C$201,Gastos!$G$5:$G$201,$B$4,Gastos!$D$5:$D$201,A17) -> 0 | D17: =B17-C17 -> 0
A18: Suscripciones | B18: =Config!B17 -> 0 | C18: =SUMIFS(Gastos!$C$5:$C$201,Gastos!$G$5:$G$201,$B$4,Gastos!$D$5:$D$201,A18) -> 0 | D18: =B18-C18 -> 0
A19: Otros | B19: =Config!B18 -> 0 | C19: =SUMIFS(Gastos!$C$5:$C$201,Gastos!$G$5:$G$201,$B$4,Gastos!$D$5:$D$201,A19) -> 0 | D19: =B19-C19 -> 0
